pylineament/__init__.py
pylineament/pylineament.py
pylineament/pylineament_ui.py
pylineament-0.1.3.dist-info/licenses/LICENSE
pylineament-0.1.3.dist-info/METADATA
pylineament-0.1.3.dist-info/WHEEL
pylineament-0.1.3.dist-info/entry_points.txt
pylineament-0.1.3.dist-info/top_level.txt
pylineament-0.1.3.dist-info/RECORD
