Metadata-Version: 2.4
Name: pylineament
Version: 0.1.3
Summary: Python Geological Lineament extraction package
Author-email: Epo Kusumah <epo.pk@universiaspertamina.ac.id>
License-Expression: MIT
Project-URL: Homepage, https://github.com/epokus/pylineament
License-File: LICENSE
Requires-Dist: affine==2.4.0
Requires-Dist: attrs==25.4.0
Requires-Dist: certifi==2025.10.5
Requires-Dist: click==8.3.0
Requires-Dist: click-plugins==1.1.1.2
Requires-Dist: cligj==0.7.2
Requires-Dist: colorama==0.4.6
Requires-Dist: fiona==1.10.1
Requires-Dist: imageio==2.37.0
Requires-Dist: joblib==1.5.2
Requires-Dist: lazy_loader==0.4
Requires-Dist: networkx==3.4.2
Requires-Dist: numpy==2.2.6
Requires-Dist: packaging==25.0
Requires-Dist: pandas==2.3.3
Requires-Dist: pillow==12.0.0
Requires-Dist: pyparsing==3.2.5
Requires-Dist: PyQt5==5.15.11
Requires-Dist: PyQt5-Qt5==5.15.2
Requires-Dist: PyQt5_sip==12.17.1
Requires-Dist: pyqtgraph==0.13.7
Requires-Dist: python-dateutil==2.9.0.post0
Requires-Dist: pytz==2025.2
Requires-Dist: rasterio==1.4.3
Requires-Dist: scikit-image==0.25.2
Requires-Dist: scikit-learn==1.7.2
Requires-Dist: scipy==1.15.3
Requires-Dist: six==1.17.0
Requires-Dist: threadpoolctl==3.6.0
Requires-Dist: tifffile==2025.5.10
Requires-Dist: tzdata==2025.2
Dynamic: license-file
